{
  "title": "{websiteName} 历史博客",
  "subtitle": "探索我们历史与考古数据平台的洞见与故事",
  "blogs": [
    {
      "id": 1,
      "title": "揭开古代美索不达米亚的秘密",
      "content": [
        "美索不达米亚常被称为文明的摇篮，是考古奇迹的宝库。{websiteName} 通过精选数据和互动工具，让您更接近苏美尔、巴比伦和亚述等古代城市。",
        "在今伊拉克的发掘中，发现了复杂的楔形文字泥板，内容涵盖贸易、天文学等多个领域。这些文物可通过 {websiteName} 获取，提供对早期文字系统的了解。",
        "巨大的阶梯式神庙（齐格拉特）是美索不达米亚宗教生活的中心。我们平台提供详细的 3D 模型，展示其宏伟建筑。",
        "考古学家发现了先进的灌溉系统，展示了古代工程师的智慧。{websiteName} 为研究人员与爱好者汇总这些数据。",
        "《吉尔伽美什史诗》是现存最古老的文学作品之一。我们的平台提供译本与解析，帮助您深入理解。",
        "像汉谟拉比法典这样的文物揭示了早期法律体系。{websiteName} 提供高清图像与专家点评。",
        "我们数据库记录了连接美索不达米亚与印度河流域的贸易网络，展现早期全球化现象。",
        "{websiteName} 还提供如乌鲁克等重要遗址的虚拟游览，让历史触手可及。",
        "通过使用 {websiteName}，您可以探索这些发现，并参与关于美索不达米亚文化的持续讨论。",
        "加入我们的社区，获取该古老地区最新的考古发现与洞察。"
      ],
      "date": "2025年8月1日",
      "location": "美索不达米亚，今伊拉克"
    },
    {
      "id": 2,
      "title": "印度河流域文明的奥秘",
      "content": [
        "兴盛于公元前2500年的印度河流域文明是最神秘的古代社会之一。{websiteName} 提供其考古记录与城市规划数据。",
        "哈拉帕与摩亨佐-达罗等城市展现了先进的城市布局与排水系统，我们平台有详细记录。",
        "带有未解读文字的印章提供了语言线索。{websiteName} 提供高质量图像与语言分析，帮助研究者。",
        "摩亨佐-达罗的大浴池是古代工程的奇迹，我们提供其交互式3D重建。",
        "与美索不达米亚及中亚的贸易联系也有详细记录，{websiteName} 制作了网络图谱。",
        "陶器与珠宝反映了丰富的物质文化，可通过我们精心策划的图库访问。",
        "平台包含专家文章，探讨该文明衰落的可能原因，如气候变化或入侵。",
        "在 {websiteName} 上的虚拟游览功能，让您在家即可探索关键遗址。",
        "我们鼓励用户在社区论坛中讨论印度河文字及其未解之谜。",
        "加入 {websiteName}，深入探索印度河流域的丰富历史，发现隐藏的故事。"
      ],
      "date": "2025年7月15日",
      "location": "印度河流域，今巴基斯坦"
    },
    {
      "id": 3,
      "title": "探索古埃及的金字塔",
      "content": [
        "埃及金字塔是古代智慧的象征，是 {websiteName} 的重要内容之一，我们提供详尽的考古数据与可视化资源。",
        "吉萨大金字塔为胡夫法老所建，是古代世界七大奇迹之一。我们平台提供其3D模型，便于探索建造过程。",
        "吉萨高原附近的发掘揭示了工人村庄，展现了金字塔工匠的生活。{websiteName} 将这些数据整合并提供访问。",
        "墓室中的象形文字揭示了埃及人关于来世的信仰。平台提供翻译与专家评论。",
        "守护金字塔的狮身人面像也是亮点之一，{websiteName} 提供其构造与功能的详尽分析。",
        "我们数据库也包括萨卡拉与达赫舒尔等不太知名的金字塔信息，扩展探索范围。",
        "{websiteName} 的虚拟现实游览功能让金字塔“活”了起来，用户可漫步古代通道。",
        "我们还发表有关建造技术的文章，探讨其巨大建筑的实现方式。",
        "通过加入 {websiteName}，您可访问独家内容，并参与埃及考古的讨论。",
        "使用 {websiteName} 的全面资源，发现金字塔的秘密与文化意义。"
      ],
      "date": "2025年6月20日",
      "location": "埃及吉萨"
    },
    {
      "id": 4,
      "title": "失落之城佩特拉：纳巴泰人的奇迹",
      "content": [
        "佩特拉，这座雕刻在约旦悬崖上的玫瑰红之城，是纳巴泰人智慧的象征。{websiteName} 提供关于这一世界遗产的大量数据。",
        "最著名的建筑“宝库”通过我们平台上的高清图像与3D模型呈现。",
        "考古发现揭示佩特拉作为贸易中心的角色，连接阿拉伯、埃及与地中海。{websiteName} 绘制了这些贸易路线。",
        "蓄水池与水坝等水利系统体现了纳巴泰人的工程才能。我们平台提供其详细研究。",
        "岩石墓葬与庙宇揭示纳巴泰人的宗教与文化，您可通过 {websiteName} 的图像库探索。",
        "虚拟游览功能让用户可在线体验佩特拉狭窄的“西克”与隐藏的宝藏。",
        "最新发掘已发现新的建筑结构，{websiteName} 将持续更新相关信息。",
        "我们收录了关于佩特拉衰落及其19世纪重新发现的专家文章。",
        "加入 {websiteName} 社区，讨论佩特拉的历史意义与考古研究。",
        "使用 {websiteName} 全面的资源，探索佩特拉的奇迹与考古遗产。"
      ],
      "date": "2025年5月10日",
      "location": "约旦佩特拉"
    } ,


    {
  "id": 5,
  "title": "哥贝克力石阵：信仰的黎明",
  "content": [
    "哥贝克力石阵被认为是世界上最早的宗教建筑之一，{websiteName}详细展示了其考古学意义。",
    "这些T形巨石柱上雕刻着动物和象征图案，反映了古代人类的信仰体系。",
    "这一遗址的存在早于农业革命，为我们理解人类精神生活提供了新视角。",
    "{websiteName}通过3D建模和详细图示展示了该遗址的布局和功能。",
    "这处位于土耳其东南部的遗址，可能是早期宗教网络的重要中心。",
    "{websiteName}持续更新关于该遗址的新研究成果和科学发现。",
    "用户可以通过虚拟导览探索该地区，仿佛亲临其境。",
    "学者们在{websiteName}上讨论其社会组织和精神文化的起源。",
    "该平台提供有关石阵建造目的的多种解释和假说。",
    "探索哥贝克力石阵，为人类文明的起点揭开新的篇章。"
  ],
  "date": "2025年6月2日",
  "location": "土耳其，尚勒乌尔法"
} ,


{
  "id": 5,
  "title": "哥贝克力石阵：信仰的黎明",
  "content": [
    "哥贝克力石阵被认为是世界上最早的宗教建筑之一，{websiteName}详细展示了其考古学意义。",
    "这些T形巨石柱上雕刻着动物和象征图案，反映了古代人类的信仰体系。",
    "这一遗址的存在早于农业革命，为我们理解人类精神生活提供了新视角。",
    "{websiteName}通过3D建模和详细图示展示了该遗址的布局和功能。",
    "这处位于土耳其东南部的遗址，可能是早期宗教网络的重要中心。",
    "{websiteName}持续更新关于该遗址的新研究成果和科学发现。",
    "用户可以通过虚拟导览探索该地区，仿佛亲临其境。",
    "学者们在{websiteName}上讨论其社会组织和精神文化的起源。",
    "该平台提供有关石阵建造目的的多种解释和假说。",
    "探索哥贝克力石阵，为人类文明的起点揭开新的篇章。"
  ],
  "date": "2025年6月2日",
  "location": "土耳其，尚勒乌尔法"
}


  ]
}
